werq/__init__.py
werq/__version.py
werq/exceptions.py
werq/py.typed
werq/queue.py
werq/cli/__init__.py
werq/cli/submit.py
werq/cli/worker.py
werq-0.6.0.dist-info/METADATA
werq-0.6.0.dist-info/WHEEL
werq-0.6.0.dist-info/entry_points.txt
werq-0.6.0.dist-info/licenses/LICENSE
werq-0.6.0.dist-info/RECORD
