Metadata-Version: 2.4
Name: werq
Version: 0.6.0
Summary: Simple directory-based job queue for Python
Author-email: Vojtech Micka <micka.vojtech@gmail.com>
License-Expression: MIT
License-File: LICENSE
Keywords: directory-queue,job-queue,queue,task-queue
Classifier: Development Status :: 3 - Alpha
Classifier: Intended Audience :: Developers
Classifier: License :: OSI Approved :: MIT License
Classifier: Operating System :: OS Independent
Classifier: Programming Language :: Python :: 3
Classifier: Programming Language :: Python :: 3.11
Classifier: Programming Language :: Python :: 3.12
Classifier: Programming Language :: Python :: 3.13
Classifier: Topic :: Software Development :: Libraries :: Python Modules
Classifier: Topic :: System :: Distributed Computing
Classifier: Typing :: Typed
Requires-Python: >=3.11
Requires-Dist: filelock>=3.16.1
Requires-Dist: rich>=13.9.4
